CTkSuggestion/__init__.py
CTkSuggestion/main.py
CTkSuggestions/__init__.py
CTkSuggestions/main.py
CTkSuggestions-0.2.2.dist-info/METADATA
CTkSuggestions-0.2.2.dist-info/WHEEL
CTkSuggestions-0.2.2.dist-info/top_level.txt
CTkSuggestions-0.2.2.dist-info/RECORD
